client/__init__.py
client/run_client.py
client/client/__init__.py
client/client/add_contact_dialog_ui.py
client/client/client_db.py
client/client/client_gui.py
client/client/client_main.py
client/client/client_main_ui.py
client/client/del_contact_dialog_ui.py
client/client/start_dialog_ui.py
client/common/__init__.py
client/common/decorators.py
client/common/errors.py
client/common/settings.py
client/common/utilites.py
client/log/__init__.py
client/log/client_log_config.py
client/log/server_log_config.py
client/tests/__init__.py
client/tests/test_client.py
client/tests/test_utilites.py
geek_mess_client-0.0.1.data/scripts/client_run
geek_mess_client-0.0.1.dist-info/METADATA
geek_mess_client-0.0.1.dist-info/WHEEL
geek_mess_client-0.0.1.dist-info/top_level.txt
geek_mess_client-0.0.1.dist-info/RECORD
